syncdirs/__init__.py
syncdirs/__main__.py
syncdirs/syncdir.py
syncdirs-0.1.6.dist-info/METADATA
syncdirs-0.1.6.dist-info/WHEEL
syncdirs-0.1.6.dist-info/entry_points.txt
syncdirs-0.1.6.dist-info/RECORD
