Metadata-Version: 2.1
Name: syncdirs
Version: 0.1.6
Summary: 
Author: Richard Filo
Author-email: risso999@gmail.com
Requires-Python: >=3.11,<4.0
Classifier: Programming Language :: Python :: 3
Classifier: Programming Language :: Python :: 3.11
Requires-Dist: schedule (>=1.2.0,<2.0.0)
